numpyslicesplit/README.MD
numpyslicesplit/__init__.py
numpyslicesplit/requirements.txt
numpyslicesplit/thirdparty.json
numpyslicesplit-0.10.dist-info/LICENSE.rst
numpyslicesplit-0.10.dist-info/METADATA
numpyslicesplit-0.10.dist-info/WHEEL
numpyslicesplit-0.10.dist-info/top_level.txt
numpyslicesplit-0.10.dist-info/RECORD
