Metadata-Version: 2.1
Name: numpyslicesplit
Version: 0.10
Summary: Splits a numpy array or a list based on the given indices or ranges and returns the split arrays.
Home-page: https://github.com/hansalemaos/numpyslicesplit
Author: Johannes Fischer
Author-email: aulasparticularesdealemaosp@gmail.com
License: MIT
Keywords: numpy
Classifier: Development Status :: 4 - Beta
Classifier: Programming Language :: Python :: 3 :: Only
Classifier: Programming Language :: Python :: 3.10
Classifier: Topic :: Software Development :: Libraries :: Python Modules
Classifier: Topic :: Utilities
License-File: LICENSE.rst
Requires-Dist: numpy
